pyodre/__init__.py
pyodre/context.py
pyodre/interpreters.py
pyodre/odre.py
pyodre/python_functions.py
pyodre/python_interpreter.py
test/__init__.py
test/test_odre_basic.py
test/test_odre_issues.py
pyodre-1.0.6.dist-info/LICENSE
pyodre-1.0.6.dist-info/METADATA
pyodre-1.0.6.dist-info/WHEEL
pyodre-1.0.6.dist-info/top_level.txt
pyodre-1.0.6.dist-info/RECORD
