Metadata-Version: 2.2
Name: pyodre
Version: 1.0.6
Summary: Open Digital Rights Enforcement Framework python implementation
Home-page: https://github.com/ODRE-Framework/odre-python
Author: Andrea Cimmino
Author-email: andreajesus.cimmino@upm.es
Classifier: Development Status :: 4 - Beta
Classifier: License :: OSI Approved :: Apache Software License
Classifier: Programming Language :: Python :: 3.9
Requires-Python: >=3.9
License-File: LICENSE
Requires-Dist: rdflib>=7.0.0
Requires-Dist: jinja2>=3.1.2
Requires-Dist: requests>=2.32.3
Dynamic: author
Dynamic: author-email
Dynamic: classifier
Dynamic: description
Dynamic: description-content-type
Dynamic: home-page
Dynamic: requires-dist
Dynamic: requires-python
Dynamic: summary
